{
  "name": "Sensor Metadata Model",
  "abbreviation": "SeMM",
  "version": 0.9,
  "releaseDate": "2017-11-29T00:00:00.000Z",
  "scope": "The Sensor Metadata Model (SeMM) describes the metadata elements of sensor or a observation time series",
  "content": {
    "General information": {
      "Name/ID\n": {
        "field_name": "title",
        "Definition": "Custom name or identifier that describes the sensor."
      },
      "UUID": {
        "field_name": "field_uuid",
        "Definition": "Unique alpha-numeric identifier of the site. The UUID is automatically generated by DEIMS-SDR.",
        "Recommendation & Hints": "The UUID is generated automatically by the system. The UUID is used for creating the URL for the site, e.g. https://data.lter-europe.net/deims/site/8eda49e9-1f4e-4f3e-b58e-e0bb25dc32a6.The UUID is taken as network independent unique identifier for the observation and experimentation facility. In addition the SITE CODE can be added as a network specific identifier.",
        "Format": "UUID (alpha-numeric)",
        "Multiplicity": "[1..1]",
        "Required": "TRUE",
        "Example": "8eda49e9-1f4e-4f3e-b58e-e0bb25dc32a6",
        "Reference List": "",
        "Comment": "automatically generated"
      },
      "Metadata update date": {
        "field_name": "field_date"
      },
      "Related Site": {
        "field_name": "field_parent_site_name"
      },
      "sensorType": {
        "field_name": "field_sensortype"
      },
      "Description": {
        "field_name": "field_description"
      },
      "Keywords": {
        "field_name": "field_keywords_envthes"
      },
      "Contact": {
        "field_name": "field_person_contact"
      }
    },
    "Geographic": {
      "Is the sensor mobile": {
        "field_name": "field_mobile"
      },
      "Position (elevation)": {
        "field_name": "field_elevation_average"
      },
      "Trajectory": {
        "field_name": "field_geo_bounding_box"
      }
    },
    "Observation": {
      "Sensor operational since": {
        "field_name": "field_publication_date"
      },
      "resultAcquisitionSource": {
        "field_name": "field_resultacquisitionsource"
      },
      "media monitored": {
        "field_name": "field_parameters_taxonomy"
      },
      "Obersation(s)": {
        "Measure": {
          "field_name": ""
        },
        "Unit of measurements": {
          "field_name": ""
        }
      }
    }
  }
}
